bvx_network/__init__.py
bvx_network/unused_port_number.py
bvx_network-0.0.9.dist-info/LICENSE
bvx_network-0.0.9.dist-info/METADATA
bvx_network-0.0.9.dist-info/WHEEL
bvx_network-0.0.9.dist-info/top_level.txt
bvx_network-0.0.9.dist-info/RECORD
